slurmtop/__about__.py
slurmtop/__init__.py
slurmtop/_data.py
slurmtop/_info_widget.py
slurmtop/_sinfo_widget.py
slurmtop/_squeue_widget.py
slurmtop/app.py
slurmtop-0.0.4.dist-info/LICENSE
slurmtop-0.0.4.dist-info/METADATA
slurmtop-0.0.4.dist-info/WHEEL
slurmtop-0.0.4.dist-info/entry_points.txt
slurmtop-0.0.4.dist-info/top_level.txt
slurmtop-0.0.4.dist-info/RECORD
