Metadata-Version: 2.1
Name: slurmtop
Version: 0.0.4
Summary: A Slurm top
Author-email: Léo Hunout <leo.hunout@gmail.com>
License: The MIT License (MIT)
Project-URL: Code, https://github.com/hunoutl/slurmtop
Project-URL: Issues, https://github.com/hunoutl/slurmtop/issues
Classifier: Development Status :: 4 - Beta
Classifier: License :: OSI Approved :: MIT License
Classifier: Operating System :: POSIX :: Linux
Classifier: Operating System :: MacOS
Classifier: Programming Language :: Python
Classifier: Programming Language :: Python :: 3
Classifier: Programming Language :: Python :: 3.7
Classifier: Programming Language :: Python :: 3.8
Classifier: Programming Language :: Python :: 3.9
Classifier: Programming Language :: Python :: 3.10
Classifier: Topic :: Utilities
Requires-Python: >=3.7
License-File: LICENSE
Requires-Dist: rich >=13.8.0
Requires-Dist: textual >=0.79.1
